{"JaUgBhLZYVP+RLiHGpGSvQ==":"sm%203d-1492x1359.png","V7DTYBEiJwC4YuLRK2dDnA==":"dsc08672-1999x1338.jpg","qJxdSRsuM0EtxXsIdb3r9w==":"salma%2011-720x479.jpg","eODHoqtVgRwCksDgKK9xuw==":"robot-2000x2250.png","HyxbO1Txe6x0ytBnQODiNA==":"stem-2000x2246.png","5akCFCwRLnq212YNfxvVaA==":"postcard%20back-1999x2252.png","Uchdv5CRHV0qqnGhK7b6dw==":"postcard%20front-2000x2249.png","60l6Ck1w9f73gYfS7fO4kg==":"stopping%20gun%20violence-2000x2250.png","VDJuR1Dd9wgD2g6gvLpaHA==":"batman%20logo-576x648.png","wzPGljoxn2Fbd+VikKcSmg==":"iron%20man%20logo-576x648.png","izIqhPjtuFNn2LtBSdcl+A==":"flash%20logo-2000x2250.png","d1dWi82bZGmIl6Gt/p6sNA==":"marvel%20symbols%20logo-576x648.png","lnsJwa51VzYE9wFl1DneaA==":"album%20front%20cover-2000x2250.png","vhQqqsktvoiqx1SqLzVxFg==":"inside%20of%20album%20cover-2000x2250.png","5MOs57CQppiNj8KxpyiyBA==":"album%20cd-2000x2250.png","3dqF+NaKfX8hel0yKtnT2g==":"3d%20robot-2000x2249.png","4ccnX5ssfpjZmMO9eIooPg==":"3d%20mas%20logo-2000x2246.png","XY3O8ChXgrsTjuajFOcQCg==":"3d%20head-2000x2247.png","wB8ZEtXVP55TrPSOANyhug==":"3d%20classroom-2000x2249.png","zdi0xjerjal2IcVbnMrzjQ==":"britto-2000x2233.png","CNLei9FZ7YlqTAwhHdHCjQ==":"retro%20car%20typography-2000x2245.png","0E4Ug+Iat44GSY2S9HTkgw==":"water%20color%20rose-2000x2250.png","zbSseVYUR6MQWeZP8iLgjg==":"photoshop%20background-2000x1125.png","n6sjiaexAgjU2yN3k6zyuQ==":"illustrator%20background-2000x1125.png","pzmAUGmOIE3FHga4UYQH5g==":"illustrator%20background-2000x1125.png","jJXorlBqYZtttrMD+DlKig==":"premiere%20background-2000x1125.png","uaWc4f4gc11wpoKVEXuvYw==":"camaro-2000x1777.png","W/Z2HghXRMcLwoZCDDVs0Q==":"camaro-2000x2246.png","wcildzr+EZLq1OriWVHKxw==":"vintage%20tv-2000x2250.png","TVSK6KG9zATt1oENO/LkgQ==":"drawing%20tv-2000x2250.png","3YpuXGGp7ymr7lt2Hx2mvw==":"lighting%20bolt-2000x2250.png","iY2iM/iPoDw4spIPETNL2A==":"name-2000x2250.png","08JYm07pAusOWuxJYig/Mw==":"postcard%20front-2000x2250.png","uFSiwLBJb5LdkNHD3+RAsw==":"postcard%20back-1999x2252.png","8a9FoFnSN6LjIHDK9HhMSw==":"robot-1-2000x2250.png","kbojl2KvYpjGNUZvEXbkmA==":"britto-1-2000x2233.png","1Ad30WoTTzHGxM85yCqYHw==":"retro%20car%20typography-2000x2245.png","YDvPd5rVzT6wca8dBDTBgA==":"drawing%20avatar-2000x2250.png","uZeNZZsH5RKJwDthzWIijg==":"avatar-2000x2250.png","pYLkJ+Z6DAv22mDsT9ZqYw==":"triple%20image-2000x2250.png","H/GiSAKgmUyxsqQXtGHXpw==":"fire%20logo-348x787.png","Z/2YPqJjkN6YNbvN5pfFbg==":"fire%20logo-164x371.png","JF79KvQvoYMIheHUNSOjsw==":"fire%20logo-122x276.png","ihlkf69UyfSmhSyJ1Jvc6w==":"jumbotron.jpg","FegeeAUSBCn++y+5QrTK1Q==":"introduction%20pic-960x960.jpg","tQJnchzN1EDi681pWvjHIg==":"comic%20by%20me-2000x2250.png","znaPRQM5ugg2PAkvpQH2bw==":"amy%20comc%201-2000x2250.png","z/J7Mjpv1ToHaHU3Iu6OnQ==":"amy%20comc%202-2000x2250.png","qU7aNYGceElaEElQ1FoS9g==":"amy%20comc%203-2000x2250.png","dXR6071UtoDoR5cEUTsM+Q==":"amy%20comc%204-2000x2250.png","h3tM6yyYA27I1xRpw59y+Q==":"amy%20comc%205-2000x2250.png","jLgWXP9KmBWpjMiNQOqZdw==":"amy%20comc%207-2000x2250.png","mxzooyVMrtqxUxYzdn8Wrw==":"amy%20comc%206-2000x2250.png","Q1YX5D7AI5so5ltvVLZQDw==":"amy%20comc%208-2000x2250.png","np6deGFRW6G4/JAQgJkFWw==":"legacies-2000x2250.png","bl+Y/UzJQVVO0JEAXotOWg==":"mas%20logo-2000x2250.png","PdYcTPxW/o+QsXWppG/lgg==":"water%20color%20rose-2000x1284.jpg","lPKobUVhZFJ2MNe0pDN5iQ==":"salma%20mohammed%20magical%20forest-2000x1167.jpg","W++pBfpKY78RRUJF5Eso4Q==":"malala%20fin-2000x2686.jpg","NRmyqdn41JHP4Tx1xQrI/A==":"microsoft-office-specialist-excel-2016-352x352.png","MV3tevGI+9dF+qlug1H07g==":"microsoft-office-specialist-excel-2016%20(1)-125x125.png","8Jn5tkoLaBpWT4u3U//vnA==":"microsoft-office-specialist-word-2016-352x352.png","mwkq3nR5/hr1aTrarUXkXQ==":"microsoft-office-specialist-word-2016-352x352.png","gw1/t/A10544NDImkUcH3Q==":"mbr-1920x1280.jpg","1vgt21XblAJMXoLKqZJxow==":"mbr-1-1920x1280.jpg","L8W8+lgEpCeWiDGo1+VO4A==":"mbr-1920x960.jpg","cPHSUtnozM7FtaarYwsZUQ==":"mbr-1920x1246.jpg","s173LwEpN3O2R3JVHhPiGw==":"mbr-1920x1440.jpg","z2hQEUOLL2VytGe/XX/GoA==":"mbr-2-1920x1280.jpg","06OqENd5fmN3UV8/bEUM3w==":"powerpoint-352x352.png"}